{
    "cargoRecrutaId": "1168128637731737600",
    "faccoes": {
        "1168129033320005712": {
            "nome": "• Marinha",
            "canalDeAnuncio": "1168925567523954738",
            "imagem": "https://i.imgur.com/GjNlGDu.png",
            "caminho": [
                { "id": "1168128637731737600", "nome": "Recruta", "custo": 0 },
                { "id": "1168129532822183956", "nome": "Marinheiro", "custo": 1 },
                { "id": "1168129653775401010", "nome": "Cabo", "custo": 3 },
                { "id": "1168129758509400085", "nome": "Terceiro Sargento", "custo": 5 },
                { "id": "1168129910543618149", "nome": "Segundo Sargento", "custo": 8 },
                { "id": "1168130006733291520", "nome": "Primeiro Sargento", "custo": 12 },
                { "id": "1168130121703690320", "nome": "Guarda Marinha", "custo": 16 },
                { "id": "1168130206660186122", "nome": "Subtenente", "custo": 21 },
                { "id": "1168130325944156230", "nome": "Segundo Tenente", "custo": 27 },
                { "id": "1168130397507305542", "nome": "Primeiro Tenente", "custo": 33 },
                { "id": "1168130492543082496", "nome": "Capitão", "custo": 40 },
                { "id": "1168130573981036644", "nome": "Capitão Tenente", "custo": 48 },
                { "id": "1168130663471063120", "nome": "Capitão de Corveta", "custo": 56 },
                { "id": "1168130833215209532", "nome": "Capitão de Fragata", "custo": 65 },
                { "id": "1168130932590247956", "nome": "Capitão de Mar e Guerra", "custo": 75 },
                { "id": "1168131013723357204", "nome": "Contra Almirante", "custo": 85 },
                { "id": "1168131093113946112", "nome": "Vice Almirante", "custo": 96 },
                { "id": "1168131174092120155", "nome": "Almirante de Esquadra", "custo": 108 },
                { "id": "1168131245089304657", "nome": "Almirante", "custo": 123 }
            ]
        },
        "1168129111300952136": {
            "nome": "• Exército",
            "canalDeAnuncio": "1168925529810141255",
            "imagem": "https://i.imgur.com/yBfXTrG.png",
            "caminho": [
                { "id": "1168128637731737600", "nome": "Recruta", "custo": 0 },
                { "id": "1168131497931587654", "nome": "Soldado", "custo": 1 },
                { "id": "1168131641014165564", "nome": "Taifeiro de 2ª classe", "custo": 3 },
                { "id": "1168131742460878898", "nome": "Taifeiro de 1ª Classe", "custo": 5 },
                { "id": "1168131846549422080", "nome": "Cabo", "custo": 8 },
                { "id": "1168131922579624026", "nome": "Taifeiro Mor", "custo": 12 },
                { "id": "1168132034177400842", "nome": "Terceiro Sargento", "custo": 16 },
                { "id": "1168132104332128266", "nome": "Segundo Sargento", "custo": 21 },
                { "id": "1168132168953188372", "nome": "Primeiro Sargento", "custo": 27 },
                { "id": "1168132225883250688", "nome": "Subtenente", "custo": 33 },
                { "id": "1168132289669570570", "nome": "Segundo Tenente", "custo": 40 },
                { "id": "1168132353109393439", "nome": "Primeiro Tenente", "custo": 48 },
                { "id": "1168132410196828230", "nome": "Capitão", "custo": 56 },
                { "id": "1168132468352614482", "nome": "Major", "custo": 65 },
                { "id": "1168132545938800650", "nome": "Tenente Coronel", "custo": 75 },
                { "id": "1168132644265328701", "nome": "General de Brigada", "custo": 85 },
                { "id": "1168132717144784947", "nome": "General de Divisão", "custo": 96 },
                { "id": "1168132782787862558", "nome": "General do Exército", "custo": 108 },
                { "id": "1168132847952678912", "nome": "Marechal", "custo": 123 }
            ]
        },
        "1168129202521976904": {
            "nome": "• Aeronáutica",
            "canalDeAnuncio": "1168925488133591140",
            "imagem": "https://i.imgur.com/4lGjYQx.png",
            "caminho": [
                { "id": "1168128637731737600", "nome": "Recruta", "custo": 0 },
                { "id": "1168133379051036733", "nome": "Taifeiro de 2ª Classe", "custo": 1 },
                { "id": "1168133469046718504", "nome": "Soldado 2ª Classe", "custo": 3 },
                { "id": "1168133544260931584", "nome": "Taifeiro de 1ª Classe", "custo": 5 },
                { "id": "1168133614995050526", "nome": "Soldado 1ª Classe", "custo": 8 },
                { "id": "1168133681423712338", "nome": "Taifeiro Mor", "custo": 12 },
                { "id": "1168133742407667793", "nome": "Cabo", "custo": 16 },
                { "id": "1168133800678531072", "nome": "Terceiro Sargento", "custo": 21 },
                { "id": "1168133860088909844", "nome": "Segundo Sargento", "custo": 27 },
                { "id": "1168133917637812234", "nome": "Primeiro Sargento", "custo": 33 },
                { "id": "1168133990868848670", "nome": "Segundo Tenente", "custo": 40 },
                { "id": "1168134047879483392", "nome": "Primeiro Tenente", "custo": 48 },
                { "id": "1168134105151246377", "nome": "Capitão", "custo": 56 },
                { "id": "1168134164741300264", "nome": "Major", "custo": 65 },
                { "id": "1168134224741670932", "nome": "Tenente Coronel", "custo": 75 },
                { "id": "1168134282361159750", "nome": "Coronel", "custo": 85 },
                { "id": "1168134346979606558", "nome": "Brigadeiro", "custo": 96 },
                { "id": "1168134415897149531", "nome": "Major Brigadeiro do Ar", "custo": 108 },
                { "id": "1168134484196196372", "nome": "Marechal do Ar", "custo": 123 }
            ]
        },
        "1168129337583620216": {
            "nome": "• Mercenários",
            "canalDeAnuncio": "1168925597972824064",
            "imagem": "https://i.imgur.com/3QGjGjB.png",
            "caminho": [
                { "id": "1168128637731737600", "nome": "Recruta", "custo": 0 },
                { "id": "1168134707255902268", "nome": "Subalterno", "custo": 1 },
                { "id": "1168134769019629638", "nome": "Escudeiro", "custo": 3 },
                { "id": "1168134825969528873", "nome": "Aprendiz", "custo": 5 },
                { "id": "1168134887309512714", "nome": "Arqueiro", "custo": 8 },
                { "id": "1168134950066266183", "nome": "Soldado", "custo": 12 },
                { "id": "1168135012579934278", "nome": "Lanceiro", "custo": 16 },
                { "id": "1168135069415510046", "nome": "Guarda", "custo": 21 },
                { "id": "1168135128033280050", "nome": "Cavaleiro", "custo": 27 },
                { "id": "1168135191264493649", "nome": "Bárbaro", "custo": 33 },
                { "id": "1168135252080398336", "nome": "Assassino", "custo": 40 },
                { "id": "1168135311231369246", "nome": "Assassino de Elite", "custo": 48 },
                { "id": "1168135371661389864", "nome": "Cavaleiro Real", "custo": 56 },
                { "id": "1168135431405043742", "nome": "Guarda Real", "custo": 65 },
                { "id": "1168135492193566730", "nome": "Paladino", "custo": 75 },
                { "id": "1168135546594410537", "nome": "Comandante", "custo": 85 },
                { "id": "1168135607907536967", "nome": "Colíder de Guilda", "custo": 96 },
                { "id": "1168135667104940052", "nome": "Líder de Guilda", "custo": 108 },
                { "id": "1168135728362438696", "nome": "Rei Mercenário", "custo": 123 }
            ]
        }
    }
}